gpt_web_crawler/__init__.py
gpt_web_crawler/main.py
gpt_web_crawler/webcrawer/__init__.py
gpt_web_crawler/webcrawer/get_screenshot.py
gpt_web_crawler/webcrawer/items.py
gpt_web_crawler/webcrawer/middlewares.py
gpt_web_crawler/webcrawer/openai_extract.py
gpt_web_crawler/webcrawer/pipelines.py
gpt_web_crawler/webcrawer/settings.py
gpt_web_crawler/webcrawer/spiders/Cat.py
gpt_web_crawler/webcrawer/spiders/Lion.py
gpt_web_crawler/webcrawer/spiders/Noob.py
gpt_web_crawler/webcrawer/spiders/Pro.py
gpt_web_crawler/webcrawer/spiders/__init__.py
gpt_web_crawler/webcrawer/tools/__init__.py
gpt_web_crawler/webcrawer/tools/screenshot.js
gpt_web_crawler-0.0.2.dist-info/LICENSE
gpt_web_crawler-0.0.2.dist-info/METADATA
gpt_web_crawler-0.0.2.dist-info/WHEEL
gpt_web_crawler-0.0.2.dist-info/top_level.txt
gpt_web_crawler-0.0.2.dist-info/RECORD
